{
  "head": {
    "title": "{{FileFormatUp}} における大文字と小文字を区別した検索を {{EnvNameShort}} で実行する",
    "description": "{{ProdFullName}} API は、{{ProgLang}} 開発者が異なるドキュメントタイプで大文字と小文字を区別した検索を実行できるようにします。"
  },
  "header": {
    "title": "大文字と小文字を区別した検索",
    "description": "{{ProdFullName}} を使用すると、{{EnvNameShort}} アプリケーションにおいて高度な大文字と小文字を区別した検索機能を実装できます。",
    "subtitle": "{{ProdFullName}}",
    "action_title": "無料でダウンロード"
  },
  "about": {
    "title": "{{ProdShortName}} とは？",
    "content": "[{{ProdFullName}}]({{PlatformLink}}) は、ドキュメント内のテキストを検索およびインデックス作成するための強力なライブラリです。PDF、Word、Excel、PowerPoint、画像、ZIPファイルなど、70以上のフォーマットをサポートし、大量のデータを効率的に処理できます。"
  },
  "more_features": {
    "title": "文書検索とインデックス作成の主な機能",
    "description": "{{ProdFullName}} を使用すれば、70以上のファイルフォーマットでテキストを簡単に検索およびインデックス作成できます。高度な検索ツールを使用して情報を手軽にアクセス・整理できます。",
    "image_description": "{{ProdShortName}} のコア機能",
    "feature_1": {
      "title": "包括的なテキスト検索",
      "content": "PDF、Wordファイル、スプレッドシート、プレゼンテーションなど、さまざまなドキュメントタイプでテキストを見つけます。正確な結果を得るために、完全一致、曖昧検索、ワイルドカードなどのオプションを使用します。"
    },
    "feature_2": {
      "title": "効率的なデータインデックス作成",
      "content": "検索を迅速化するためにインデックスを作成および管理します。インデックス作成により、大規模なドキュメントコレクション内のデータを整理し、すばやく見つけることができます。"
    },
    "feature_3": {
      "title": "複数言語のサポート",
      "content": "80以上の言語でドキュメントを検索でき、多様なキーボードレイアウトや単語の変形に対応しており、正確な検索結果を保証します。"
    },
    "feature_4": {
      "title": "カスタマイズ可能な検索設定",
      "content": "大文字と小文字を区別する設定、日付フィルター、インデックス作成中に特定の用語やデータを除外します。"
    }
  },
  "formats": {
    "title": "対応ドキュメントフォーマット",
    "description": "{{ProdShortName}} は70以上のドキュメントフォーマットをサポートしています。検索オプションをカスタマイズし、インデックス作成で時間を節約できます。"
  },
  "operations": {
    "title": "主要機能",
    "description": "高速かつ正確なドキュメント検索のための高度な機能を探索します。"
  },
  "examples": {
    "comment_1": "インデックスフォルダーのパスを指定します",
    "comment_2": "検索するドキュメントが含まれるフォルダーを設定します",
    "comment_3": "設定で大文字と小文字を区別した検索を有効にします",
    "comment_4": "検索を実行します"
  },
  "steps": {
    "title": "{{FileFormatUp}} ファイルでの大文字と小文字を区別した検索の手順",
    "content": {
      "title": "[{{ProdShortName}}]({{PlatformLink}}) を使用すれば、{{FileFormatUp}} ファイルで大文字と小文字を区別した検索を実行し、{{EnvName}} のワークフローを強化します。",
      "step_1": "検索インデックスを保存するフォルダーをセットアップします。",
      "step_2": "{{FileFormatUp}} ファイルが含まれるフォルダーを選択します。",
      "step_3": "検索を実行して結果を取得します。",
      "step_4": "結果を処理して使用します。"
    }
  },
  "code_1": {
    "title": "例：大文字と小文字を区別した検索の実装",
    "content": "この例では、{{FileFormatUp}} ドキュメントの大文字と小文字を区別した検索を実行する方法を示します。",
    "comment_1": "検索インデックスのフォルダーを定義します",
    "comment_2": "ドキュメントフォルダーへのパスを提供します",
    "comment_3": "検索クエリをセットアップします",
    "comment_4": "大文字と小文字を区別した検索設定を有効にします",
    "comment_5": "ドキュメント内のテキストを検索します",
    "comment_6": "結果を処理および扱います"
  }
}